bash2_magic/__init__.py
bash2_magic/bash2_magic.py
nbfancy/__init__.py
nbfancy/__main__.py
nbfancy/globalconf.py
nbfancy/nbfancy_tools.py
nbfancy/config/box.ipynb
nbfancy/config/footer.ipynb
nbfancy/config/header.ipynb
nbfancy/config/keywords.cfg
nbfancy/config/.ipynb_checkpoints/footer-checkpoint.ipynb
nbfancy/config/.ipynb_checkpoints/header-checkpoint.ipynb
nbfancy/template/00_schedule.ipynb
nbfancy/template/01_untitled_episode.ipynb
nbfancy/template/99_episode_template.ipynb
nbfancy/template/.ipynb_checkpoints/00_schedule-checkpoint.ipynb
nbfancy/template/.ipynb_checkpoints/01_episode-checkpoint.ipynb
nbfancy/template/.ipynb_checkpoints/01_untitled_episode-checkpoint.ipynb
nbfancy/template/.ipynb_checkpoints/99_episode_template-checkpoint.ipynb
nbfancy/template/.ipynb_checkpoints/trial-checkpoint.ipynb
nbfancy/tools/custom.css
nbfancy/tools/example_gitignore
nbfancy/tools/redirect.html
nbfancy/tools/css/custom.css
nbfancy/tools/css/font-awesome.css
nbfancy/tools/css/fontawesome-webfont.ttf
nbfancy/tools/css/w3.css
nbfancy/tools/css/css/favicon.png
nbfancy/tools/css/css/font-awesome.css
nbfancy/tools/css/css/fontawesome-webfont.ttf
nbfancy/tools/css/css/w3.css
nbfancy/tutorial/00_schedule.ipynb
nbfancy/tutorial/01_episode.ipynb
nbfancy/tutorial/01_motivation.ipynb
nbfancy/tutorial/02_episode.ipynb
nbfancy/tutorial/02_installation.ipynb
nbfancy/tutorial/03_build.ipynb
nbfancy/tutorial/03_episode.ipynb
nbfancy/tutorial/04_episode.ipynb
nbfancy/tutorial/04_files.ipynb
nbfancy/tutorial/05_environments.ipynb
nbfancy/tutorial/05_episode.ipynb
nbfancy/tutorial/06_episode.ipynb
nbfancy/tutorial/06_git.ipynb
nbfancy/tutorial/07_episode.ipynb
nbfancy/tutorial/07_multicell.ipynb
nbfancy/tutorial/08_keywords.ipynb
nbfancy/tutorial/09_template.ipynb
nbfancy/tutorial/10_magic.ipynb
nbfancy/tutorial/11_slides.ipynb
nbfancy/tutorial/12_contributing.ipynb
nbfancy/tutorial/99_episode_template.ipynb
nbfancy/tutorial/.ipynb_checkpoints/00_schedule-checkpoint.ipynb
nbfancy-0.1a3.dist-info/LICENSE
nbfancy-0.1a3.dist-info/METADATA
nbfancy-0.1a3.dist-info/WHEEL
nbfancy-0.1a3.dist-info/entry_points.txt
nbfancy-0.1a3.dist-info/top_level.txt
nbfancy-0.1a3.dist-info/RECORD
