Metadata-Version: 2.1
Name: nbfancy
Version: 0.1a3
Summary: Tools for rendering notebooks suitable for teaching
Home-page: https://github.com/JDBetteridge/nbfancy
Author: Jack Betteridge
Author-email: J.D.Betteridge@Bath.ac.uk
License: UNKNOWN
Platform: UNKNOWN
Classifier: Programming Language :: Python :: 3
Classifier: License :: OSI Approved :: BSD License
Classifier: Operating System :: POSIX :: Linux
Requires-Dist: ipython (>=6)
Requires-Dist: notebook (==5.7.10)
